MANIFEST.in
README.txt
setup.cfg
setup.py
docs/HISTORY.txt
docs/HISTORY.txt~
docs/INSTALL.txt
docs/LICENSE.GPL
docs/LICENSE.txt
quintagroup/__init__.py
quintagroup/__init__.pyc
quintagroup.plonegooglesitemaps.egg-info/PKG-INFO
quintagroup.plonegooglesitemaps.egg-info/SOURCES.txt
quintagroup.plonegooglesitemaps.egg-info/dependency_links.txt
quintagroup.plonegooglesitemaps.egg-info/entry_points.txt
quintagroup.plonegooglesitemaps.egg-info/namespace_packages.txt
quintagroup.plonegooglesitemaps.egg-info/not-zip-safe
quintagroup.plonegooglesitemaps.egg-info/requires.txt
quintagroup.plonegooglesitemaps.egg-info/top_level.txt
quintagroup/plonegooglesitemaps/README.txt
quintagroup/plonegooglesitemaps/__init__.py
quintagroup/plonegooglesitemaps/config.py
quintagroup/plonegooglesitemaps/configure.zcml
quintagroup/plonegooglesitemaps/events.py
quintagroup/plonegooglesitemaps/filters.py
quintagroup/plonegooglesitemaps/filters.txt
quintagroup/plonegooglesitemaps/handlers.py
quintagroup/plonegooglesitemaps/indexers.py
quintagroup/plonegooglesitemaps/interfaces.py
quintagroup/plonegooglesitemaps/overrides.zcml
quintagroup/plonegooglesitemaps/profiles.zcml
quintagroup/plonegooglesitemaps/setuphandlers.py
quintagroup/plonegooglesitemaps/upgrades.py
quintagroup/plonegooglesitemaps/utils.py
quintagroup/plonegooglesitemaps/Extensions/Install.py
quintagroup/plonegooglesitemaps/Extensions/__init__.py
quintagroup/plonegooglesitemaps/Extensions/ping_googlesitemap.py
quintagroup/plonegooglesitemaps/browser/__init__.py
quintagroup/plonegooglesitemaps/browser/commonview.py
quintagroup/plonegooglesitemaps/browser/configletview.py
quintagroup/plonegooglesitemaps/browser/configure.zcml
quintagroup/plonegooglesitemaps/browser/mobilesitemapview.py
quintagroup/plonegooglesitemaps/browser/newssitemapview.py
quintagroup/plonegooglesitemaps/browser/sitemapview.py
quintagroup/plonegooglesitemaps/browser/utils.py
quintagroup/plonegooglesitemaps/browser/images/trash.gif
quintagroup/plonegooglesitemaps/browser/resources/verify_file.css
quintagroup/plonegooglesitemaps/browser/templates/mobilesitemapview.pt
quintagroup/plonegooglesitemaps/browser/templates/newssitemapview.pt
quintagroup/plonegooglesitemaps/browser/templates/sitemapview.pt
quintagroup/plonegooglesitemaps/content/__init__.py
quintagroup/plonegooglesitemaps/content/configure.zcml
quintagroup/plonegooglesitemaps/content/newsextender.py
