Metadata-Version: 1.0
Name: quintagroup.plonegooglesitemaps
Version: 1.8.2
Summary: Allows Plone websites to get better visibility for Google search engine
Home-page: http://svn.quintagroup.com/products/quintagroup.plonegooglesitemaps
Author: Quintagroup
Author-email: info@quintagroup.com
License: GPL
Keywords: plone google sitemap quintagroup search engine
Platform: UNKNOWN
Classifier: Development Status :: 5 - Production/Stable
Classifier: Environment :: Web Environment
Classifier: Framework :: Plone :: 3.2
Classifier: Framework :: Plone :: 3.3
Classifier: Framework :: Plone :: 4.0
Classifier: Framework :: Plone :: 4.1
Classifier: Framework :: Plone :: 4.2
Classifier: Framework :: Plone :: 4.3
Classifier: Framework :: Plone
Classifier: Framework :: Zope2
Classifier: Framework :: Zope3
Classifier: License :: OSI Approved :: GNU General Public License (GPL)
Classifier: Operating System :: OS Independent
Classifier: Programming Language :: Python
